cellmap/__init__.py
cellmap/cellmap.py
cellmap-1.0.7.dist-info/METADATA
cellmap-1.0.7.dist-info/WHEEL
cellmap-1.0.7.dist-info/RECORD
