Metadata-Version: 2.1
Name: cellmap
Version: 1.0.7
Summary: CellMap - RNA landscape inference method
Home-page: https://github.com/yusuke-imoto-lab/CellMap
Author: Yusuke Imoto
Requires-Python: >=3.7
Classifier: Programming Language :: Python :: 3
Classifier: Programming Language :: Python :: 3.7
Classifier: Programming Language :: Python :: 3.8
Classifier: Programming Language :: Python :: 3.9
Classifier: Programming Language :: Python :: 3.10
Classifier: Programming Language :: Python :: 3.11
Requires-Dist: adjustText (>=0.8)
Requires-Dist: anndata (>=0.8.0)
Requires-Dist: matplotlib (>=3.7.1)
Requires-Dist: nbformat (>=4.2.0)
Requires-Dist: numpy (>=1.20)
Requires-Dist: plotly (>=5.14.1)
Requires-Dist: scanpy (>=1.9.3)
Requires-Dist: scikit-learn (>=0.24)
Requires-Dist: scipy (>=1.8.1)
Requires-Dist: scvelo (>=0.2.5)
Project-URL: Documentation, https://github.com/yusuke-imoto-lab/CellMap/
Project-URL: Repository, https://github.com/yusuke-imoto-lab/CellMap
